data_manipulation_utilities-0.2.7.data/scripts/publish
dmu/arrays/utilities.py
dmu/generic/hashing.py
dmu/generic/utilities.py
dmu/generic/version_management.py
dmu/logging/log_store.py
dmu/ml/cv_classifier.py
dmu/ml/cv_diagnostics.py
dmu/ml/cv_predict.py
dmu/ml/train_mva.py
dmu/ml/utilities.py
dmu/pdataframe/utilities.py
dmu/plotting/fwhm.py
dmu/plotting/matrix.py
dmu/plotting/plotter.py
dmu/plotting/plotter_1d.py
dmu/plotting/plotter_2d.py
dmu/plotting/utilities.py
dmu/rdataframe/atr_mgr.py
dmu/rdataframe/utilities.py
dmu/rfile/rfprinter.py
dmu/rfile/utilities.py
dmu/stats/fitter.py
dmu/stats/function.py
dmu/stats/gof_calculator.py
dmu/stats/minimizers.py
dmu/stats/model_factory.py
dmu/stats/utilities.py
dmu/stats/zfit_models.py
dmu/stats/zfit_plotter.py
dmu/testing/utilities.py
dmu/text/transformer.py
dmu_data/__init__.py
dmu_data/ml/tests/diagnostics_from_file.yaml
dmu_data/ml/tests/diagnostics_from_model.yaml
dmu_data/ml/tests/diagnostics_multiple_methods.yaml
dmu_data/ml/tests/diagnostics_overlay.yaml
dmu_data/ml/tests/train_mva.yaml
dmu_data/ml/tests/train_mva_with_diagnostics.yaml
dmu_data/plotting/tests/2d.yaml
dmu_data/plotting/tests/fig_size.yaml
dmu_data/plotting/tests/high_stat.yaml
dmu_data/plotting/tests/legend.yaml
dmu_data/plotting/tests/name.yaml
dmu_data/plotting/tests/no_bounds.yaml
dmu_data/plotting/tests/normalized.yaml
dmu_data/plotting/tests/plug_fwhm.yaml
dmu_data/plotting/tests/plug_stats.yaml
dmu_data/plotting/tests/simple.yaml
dmu_data/plotting/tests/stats.yaml
dmu_data/plotting/tests/styling.yaml
dmu_data/plotting/tests/title.yaml
dmu_data/plotting/tests/weights.yaml
dmu_data/text/transform.toml
dmu_data/text/transform.txt
dmu_data/text/transform_set.toml
dmu_data/text/transform_set.txt
dmu_data/text/transform_trf.txt
dmu_scripts/git/publish
dmu_scripts/physics/check_truth.py
dmu_scripts/rfile/compare_root_files.py
dmu_scripts/rfile/print_trees.py
dmu_scripts/ssh/coned.py
dmu_scripts/text/transform_text.py
data_manipulation_utilities-0.2.7.dist-info/METADATA
data_manipulation_utilities-0.2.7.dist-info/WHEEL
data_manipulation_utilities-0.2.7.dist-info/entry_points.txt
data_manipulation_utilities-0.2.7.dist-info/top_level.txt
data_manipulation_utilities-0.2.7.dist-info/RECORD
