Metadata-Version: 2.4
Name: data_manipulation_utilities
Version: 0.2.7
Requires-Dist: logzero
Requires-Dist: PyYAML
Requires-Dist: scipy
Requires-Dist: awkward
Requires-Dist: tqdm
Requires-Dist: numpy
Requires-Dist: toml
Requires-Dist: numpy
Requires-Dist: matplotlib
Requires-Dist: mplhep
Requires-Dist: hist[plot]
Requires-Dist: pandas
Provides-Extra: fit
Requires-Dist: zfit; extra == "fit"
Requires-Dist: tensorflow==2.18.0; extra == "fit"
Provides-Extra: ml
Requires-Dist: scikit-learn; extra == "ml"
Requires-Dist: joblib; extra == "ml"
Provides-Extra: dev
Requires-Dist: pytest; extra == "dev"
